{
  "hash": "c9f501d8",
  "configHash": "587fa1db",
  "lockfileHash": "accf6712",
  "browserHash": "7a59ad18",
  "optimized": {
    "react": {
      "src": "../../node_modules/react/index.js",
      "file": "react.js",
      "fileHash": "5606eabd",
      "needsInterop": true
    },
    "react-dom/client": {
      "src": "../../node_modules/react-dom/client.js",
      "file": "react-dom_client.js",
      "fileHash": "294b7c29",
      "needsInterop": true
    },
    "react-router-dom": {
      "src": "../../node_modules/react-router-dom/dist/index.js",
      "file": "react-router-dom.js",
      "fileHash": "70e5c0b8",
      "needsInterop": false
    },
    "@fortawesome/react-fontawesome": {
      "src": "../../node_modules/@fortawesome/react-fontawesome/index.es.js",
      "file": "@fortawesome_react-fontawesome.js",
      "fileHash": "9695470b",
      "needsInterop": false
    },
    "@fortawesome/free-solid-svg-icons": {
      "src": "../../node_modules/@fortawesome/free-solid-svg-icons/index.mjs",
      "file": "@fortawesome_free-solid-svg-icons.js",
      "fileHash": "5c07d371",
      "needsInterop": false
    },
    "sweetalert2": {
      "src": "../../node_modules/sweetalert2/dist/sweetalert2.esm.all.js",
      "file": "sweetalert2.js",
      "fileHash": "db600c19",
      "needsInterop": false
    },
    "axios": {
      "src": "../../node_modules/axios/index.js",
      "file": "axios.js",
      "fileHash": "4de64933",
      "needsInterop": false
    }
  },
  "chunks": {
    "chunk-TNTPHDQH": {
      "file": "chunk-TNTPHDQH.js"
    },
    "chunk-32E4H3EV": {
      "file": "chunk-32E4H3EV.js"
    },
    "chunk-G3PMV62Z": {
      "file": "chunk-G3PMV62Z.js"
    }
  }
}